connectome_interpreter/__init__.py
connectome_interpreter/_version.py
connectome_interpreter/activation_maximisation.py
connectome_interpreter/compress_paths.py
connectome_interpreter/external_map.py
connectome_interpreter/external_paths.py
connectome_interpreter/path_finding.py
connectome_interpreter/utils.py
connectome_interpreter/data/Badel2016/Badel2016.csv
connectome_interpreter/data/Badel2016/Badel_et_al_2016_raw.xls
connectome_interpreter/data/DoOR/door_chemical_meta.csv
connectome_interpreter/data/DoOR/door_receptor_mappings.csv
connectome_interpreter/data/DoOR/door_response_matrix.csv
connectome_interpreter/data/DoOR/processed_door_adult.csv
connectome_interpreter/data/DoOR/processed_door_adult_sfr_subtracted.csv
connectome_interpreter/data/Dweck2018/1-s2.0-S2211124718306636-mmc2.xlsx
connectome_interpreter/data/Dweck2018/1-s2.0-S2211124718306636-mmc3.xlsx
connectome_interpreter/data/Dweck2018/1-s2.0-S2211124718306636-mmc4.xlsx
connectome_interpreter/data/Dweck2018/adult_chem2glom.csv
connectome_interpreter/data/Dweck2018/adult_fruit2glom.csv
connectome_interpreter/data/Dweck2018/larva_chem2or.csv
connectome_interpreter/data/Dweck2018/larva_fruit2or.csv
connectome_interpreter/data/Matsliah2024/fafb_right_vis_cols.csv
connectome_interpreter/data/Nern2024/ME-columnar-cells-hex-location.csv
connectome_interpreter/data/Zhao2024/ucl_hex_right_20240701_tomale.csv
connectome_interpreter-2.9.5.dist-info/licenses/LICENSE
docs/conf.py
tests/__init__.py
tests/test_act_max.py
tests/test_compress_paths.py
tests/test_path_finding.py
tests/test_utils.py
connectome_interpreter-2.9.5.dist-info/METADATA
connectome_interpreter-2.9.5.dist-info/WHEEL
connectome_interpreter-2.9.5.dist-info/top_level.txt
connectome_interpreter-2.9.5.dist-info/RECORD
