Metadata-Version: 2.4
Name: connectome_interpreter
Version: 2.9.5
Summary: A tool for connectomics data interpretation
Author-email: Yijie Yin <yy432@cam.ac.uk>
License: MIT License
Project-URL: Source & example notebooks, https://github.com/YijieYin/connectome_interpreter
Project-URL: Documentation, https://connectome-interpreter.readthedocs.io/en/latest/
Keywords: connectomics,neural network
License-File: LICENSE
Requires-Dist: numpy
Requires-Dist: pandas
Requires-Dist: scipy
Requires-Dist: tqdm
Requires-Dist: plotly
Requires-Dist: matplotlib
Requires-Dist: networkx
Requires-Dist: seaborn
Requires-Dist: ipywidgets
Requires-Dist: IPython
Requires-Dist: torch
Provides-Extra: get-ngl-link
Requires-Dist: nglscenes; extra == "get-ngl-link"
Provides-Extra: wandb
Requires-Dist: wandb; extra == "wandb"
Provides-Extra: compute-flow-hitting-time
Requires-Dist: navis; extra == "compute-flow-hitting-time"
Provides-Extra: plot-layered-paths
Requires-Dist: pyvis; extra == "plot-layered-paths"
Dynamic: license-file
